pay_attention_pipeline/__init__.py
pay_attention_pipeline/pipeline/__init__.py
pay_attention_pipeline/pipeline/main_pipeline.py
pay_attention_pipeline/src/GUIDE.py
pay_attention_pipeline/src/__init__.py
pay_attention_pipeline/src/metrics.py
pay_attention_pipeline/tests/__init__.py
pay_attention_pipeline/tests/tests.py
pay_attention_pipeline-0.2.0.dist-info/METADATA
pay_attention_pipeline-0.2.0.dist-info/WHEEL
pay_attention_pipeline-0.2.0.dist-info/top_level.txt
pay_attention_pipeline-0.2.0.dist-info/RECORD
