Metadata-Version: 2.1
Name: pay-attention-pipeline
Version: 0.2.0
Summary: A pipeline for computing **Influence** and performing **Generation with GUIDE** to enhance transformer model explainability and performance.
Home-page: https://github.com/netop-team/pay_attention_pipeline
Author: Pedro Silva
Author-email: pedrolmssilva@gmail.com
Classifier: Programming Language :: Python :: 3
Classifier: License :: OSI Approved :: MIT License
Classifier: Operating System :: OS Independent
Requires-Python: >=3.6
Requires-Dist: torch>=2.4.0
Requires-Dist: transformers>=4.44.2
